LICENSE
README.md
__init__.py
anyimport.py
setup.cfg
setup.py
anyimport.egg-info/PKG-INFO
anyimport.egg-info/SOURCES.txt
anyimport.egg-info/dependency_links.txt
anyimport.egg-info/top_level.txt