Metadata-Version: 2.1
Name: anyimport
Version: 0.1
Summary: import your python file in either absoluet or relative path
Home-page: https://github.com/shuson/anyimport
Download-URL: https://github.com/shuson/anyimport/dist/anyimport-0_1.tar.gz
Author: Shuson
Author-email: wlgq@hotmail.com
License: MIT
Keywords: import,easy,relative,module
Classifier: Development Status :: 3 - Alpha
Classifier: Intended Audience :: Developers
Classifier: Topic :: Software Development :: Build Tools
Classifier: License :: OSI Approved :: MIT License
Classifier: Programming Language :: Python :: 2
Classifier: Programming Language :: Python :: 3
Classifier: Programming Language :: Python :: 3.6
Classifier: Programming Language :: Python :: 3.7
Classifier: Programming Language :: Python :: 3.8
Classifier: Programming Language :: Python :: 3.9
Classifier: Programming Language :: Python :: 3.10
License-File: LICENSE
